gitads_pypi/__init__.py
gitads_pypi/main.py
gitads_pypi-0.1.5.dist-info/licenses/LICENSE
gitads_pypi-0.1.5.dist-info/METADATA
gitads_pypi-0.1.5.dist-info/WHEEL
gitads_pypi-0.1.5.dist-info/entry_points.txt
gitads_pypi-0.1.5.dist-info/top_level.txt
gitads_pypi-0.1.5.dist-info/RECORD
