Metadata-Version: 2.4
Name: gitads-pypi
Version: 0.1.5
Summary: A simple Hello World PyPI package
Home-page: https://github.com/yourusername/gitads-pypi
Author: Your Name
Author-email: Salman Qureshi <salman@cosmicstack.org>
License: MIT
Project-URL: Homepage, https://github.com/yourusername/gitads-pypi
Project-URL: Repository, https://github.com/yourusername/gitads-pypi
Project-URL: Issues, https://github.com/yourusername/gitads-pypi/issues
Classifier: Development Status :: 3 - Alpha
Classifier: Intended Audience :: Developers
Classifier: License :: OSI Approved :: MIT License
Classifier: Operating System :: OS Independent
Classifier: Programming Language :: Python :: 3
Requires-Python: >=3.7
License-File: LICENSE
Dynamic: author
Dynamic: home-page
Dynamic: license-file
Dynamic: requires-python
